adibomb-0.1.0.dist-info/licenses/LICENSE
utils/__init__.py
utils/decorators.py
utils/provider.py
adibomb-0.1.0.dist-info/METADATA
adibomb-0.1.0.dist-info/WHEEL
adibomb-0.1.0.dist-info/top_level.txt
adibomb-0.1.0.dist-info/RECORD
