Metadata-Version: 2.4
Name: Adibomb
Version: 0.1.0
Summary: A best sms bomber existed
Home-page: https://github.com/skvinderr/Adibombomb
Author: Aditya
Author-email: skvinderr@gmail.com
Classifier: Programming Language :: Python :: 3
Classifier: License :: OSI Approved :: MIT License
Classifier: Operating System :: OS Independent
Requires-Python: >=3.6
License-File: LICENSE
Dynamic: author
Dynamic: author-email
Dynamic: classifier
Dynamic: description
Dynamic: description-content-type
Dynamic: home-page
Dynamic: license-file
Dynamic: requires-python
Dynamic: summary
